oneNeuron/__init__.py
oneNeuron/perceptron.py
first_pypi_package_DeepranjanG-0.0.1.dist-info/METADATA
first_pypi_package_DeepranjanG-0.0.1.dist-info/WHEEL
first_pypi_package_DeepranjanG-0.0.1.dist-info/top_level.txt
first_pypi_package_DeepranjanG-0.0.1.dist-info/RECORD
